{
    "document_number": "2025-10790",
    "pdf_url": "https://www.govinfo.gov/content/pkg/FR-2025-06-11/pdf/2025-10790.pdf",
    "publication_date": "2025-06-11",
    "title": "National Ocean Month, 2025",
    "summary": "The document is a proclamation by President Donald J. Trump, declaring June 2025 as National Ocean Month. It emphasizes the importance of the United States' oceans in national identity, economy, and security. The President outlines his administration's commitment to restoring maritime dominance through various initiatives, including renaming the largest gulf to the Gulf of America and signing an Executive Order to enhance domestic capabilities for exploring and processing critical minerals from the seabed. Additionally, the proclamation highlights efforts to boost American seafood competitiveness and open the Pacific Remote Islands National Monument to commercial fishing. The overarching theme is a call for Americans to appreciate the oceans' value for security, environment, economy, and recreation, reinforcing the administration's vision of a prosperous future through maritime resources.",
    "doc_type": "proclamation"
}